defendai_wozway/__init__.py
defendai_wozway/_hooks/__init__.py
defendai_wozway/_hooks/registration.py
defendai_wozway/_hooks/sdkhooks.py
defendai_wozway/_hooks/types.py
defendai_wozway/_version.py
defendai_wozway/activities.py
defendai_wozway/api_keys.py
defendai_wozway/applications.py
defendai_wozway/basesdk.py
defendai_wozway/connections.py
defendai_wozway/httpclient.py
defendai_wozway/incidents.py
defendai_wozway/models/__init__.py
defendai_wozway/models/apierror.py
defendai_wozway/models/delete_api_keyop.py
defendai_wozway/models/delete_applicationop.py
defendai_wozway/models/delete_connection_id_op.py
defendai_wozway/models/delete_policyop.py
defendai_wozway/models/delete_userop.py
defendai_wozway/models/get_activitiesop.py
defendai_wozway/models/get_applicationsop.py
defendai_wozway/models/get_connectionsop.py
defendai_wozway/models/get_incidentsop.py
defendai_wozway/models/get_policiesop.py
defendai_wozway/models/get_usersop.py
defendai_wozway/models/post_applicationop.py
defendai_wozway/models/post_connectionop.py
defendai_wozway/models/post_forgotpasswordop.py
defendai_wozway/models/post_policyop.py
defendai_wozway/models/post_resolve_incidentop.py
defendai_wozway/models/post_userop.py
defendai_wozway/models/put_policyop.py
defendai_wozway/models/put_userop.py
defendai_wozway/models/security.py
defendai_wozway/policies.py
defendai_wozway/py.typed
defendai_wozway/sdk.py
defendai_wozway/sdkconfiguration.py
defendai_wozway/types/__init__.py
defendai_wozway/types/basemodel.py
defendai_wozway/users.py
defendai_wozway/utils/__init__.py
defendai_wozway/utils/annotations.py
defendai_wozway/utils/enums.py
defendai_wozway/utils/eventstreaming.py
defendai_wozway/utils/forms.py
defendai_wozway/utils/headers.py
defendai_wozway/utils/logger.py
defendai_wozway/utils/metadata.py
defendai_wozway/utils/queryparams.py
defendai_wozway/utils/requestbodies.py
defendai_wozway/utils/retries.py
defendai_wozway/utils/security.py
defendai_wozway/utils/serializers.py
defendai_wozway-0.1.2.dist-info/METADATA
defendai_wozway-0.1.2.dist-info/WHEEL
defendai_wozway-0.1.2.dist-info/RECORD
